{
  "sections": {
    "main": {
      "type": "main-product",
      "blocks": {
        "vendor": {
          "type": "text",
          "settings": {
            "text": "{{ product.vendor }}",
            "text_style": "uppercase"
          }
        },
        "title": {
          "type": "title",
          "settings": {
          }
        },
        "price": {
          "type": "price",
          "settings": {
          }
        },
        "variant_picker": {
          "type": "variant_picker",
          "settings": {
            "picker_type": "button",
            "swatch_shape": "circle"
          }
        },
        "quantity_selector": {
          "type": "quantity_selector",
          "settings": {
          }
        },
        "buy_buttons": {
          "type": "buy_buttons",
          "settings": {
            "show_dynamic_checkout": true,
            "show_gift_card_recipient": true
          }
        },
        "description": {
          "type": "description",
          "settings": {
          }
        },
        "share": {
          "type": "share",
          "settings": {
            "share_label": "Share"
          }
        }
      },
      "block_order": [
        "vendor",
        "title",
        "price",
        "variant_picker",
        "quantity_selector",
        "buy_buttons",
        "description",
        "share"
      ],
      "custom_css": [
        "button.product-form__submit.button--full-width {background-color: #6bc993; color: white;}"
      ],
      "settings": {
        "enable_sticky_info": true,
        "color_scheme": "scheme-1",
        "media_size": "large",
        "constrain_to_viewport": true,
        "media_fit": "contain",
        "gallery_layout": "stacked",
        "media_position": "left",
        "image_zoom": "lightbox",
        "mobile_thumbnails": "hide",
        "hide_variants": true,
        "enable_video_looping": false,
        "padding_top": 36,
        "padding_bottom": 12
      }
    },
    "custom_liquid_9qczp4": {
      "type": "custom-liquid",
      "disabled": true,
      "settings": {
        "custom_liquid": "<div id=\"stamped-main-widget\" \ndata-widget-style=\"standard\"\ndata-product-id=\"{{ product.id }}\" \ndata-name=\"{{ product.title | escape }}\" \ndata-url=\"{{ shop.url }}{{ product.url }}\" \ndata-image-url=\"{{ product.featured_image | product_img_url: \"large\" |replace: '?', '%3F' | replace: '&','%26'}}\" \ndata-description=\"{{ product.description | escape }}\" \ndata-product-sku=\"{{product.selected_or_first_available_variant.sku}}\"\ndata-product-type=\"{{product.type}}\"\ndata-widget-language =\"{{ request.locale.iso_code }}\"> \n<\/div>",
        "color_scheme": "",
        "padding_top": 0,
        "padding_bottom": 0
      }
    },
    "related-products": {
      "type": "related-products",
      "settings": {
        "heading": "You may also like",
        "heading_size": "h2",
        "products_to_show": 4,
        "columns_desktop": 4,
        "color_scheme": "scheme-1",
        "image_ratio": "adapt",
        "image_shape": "default",
        "show_secondary_image": true,
        "show_vendor": false,
        "show_rating": false,
        "columns_mobile": "2",
        "padding_top": 36,
        "padding_bottom": 28
      }
    }
  },
  "order": [
    "main",
    "custom_liquid_9qczp4",
    "related-products"
  ]
}
